cdk_eksdistro/__init__.py
cdk_eksdistro/py.typed
cdk_eksdistro/_jsii/__init__.py
cdk_eksdistro/_jsii/cdk-eksdistro@2.0.13.jsii.tgz
cdk_eksdistro-2.0.13.dist-info/LICENSE
cdk_eksdistro-2.0.13.dist-info/METADATA
cdk_eksdistro-2.0.13.dist-info/WHEEL
cdk_eksdistro-2.0.13.dist-info/top_level.txt
cdk_eksdistro-2.0.13.dist-info/RECORD
